MANIFEST.in
README.rst
setup.py
docs/HISTORY.txt
monet/__init__.py
monet.calendar.extensions.egg-info/PKG-INFO
monet.calendar.extensions.egg-info/SOURCES.txt
monet.calendar.extensions.egg-info/dependency_links.txt
monet.calendar.extensions.egg-info/entry_points.txt
monet.calendar.extensions.egg-info/namespace_packages.txt
monet.calendar.extensions.egg-info/not-zip-safe
monet.calendar.extensions.egg-info/requires.txt
monet.calendar.extensions.egg-info/top_level.txt
monet/calendar/__init__.py
monet/calendar/extensions/__init__.py
monet/calendar/extensions/config.py
monet/calendar/extensions/configure.zcml
monet/calendar/extensions/exportimport.py
monet/calendar/extensions/i18n.sh
monet/calendar/extensions/interfaces.py
monet/calendar/extensions/browser/__init__.py
monet/calendar/extensions/browser/configure.zcml
monet/calendar/extensions/browser/manage_calendars.py
monet/calendar/extensions/browser/menu.py
monet/calendar/extensions/browser/monet_events_view.pt
monet/calendar/extensions/browser/monetsearchevent.pt
monet/calendar/extensions/browser/monetsearchevents.py
monet/calendar/extensions/browser/searchbar.pt
monet/calendar/extensions/browser/usefulforsearch.py
monet/calendar/extensions/browser/viewlets.py
monet/calendar/extensions/browser/javascript/monetcalendar-datepicker.js
monet/calendar/extensions/browser/stylesheets/monetcalendarsearchevent.css
monet/calendar/extensions/i18n/plone-monet.calendar.extensions-it.po
monet/calendar/extensions/i18n/plone-monet.calendar.extensions.pot
monet/calendar/extensions/locales/monet.calendar.extensions-manual.pot
monet/calendar/extensions/locales/monet.calendar.extensions.pot
monet/calendar/extensions/locales/it/LC_MESSAGES/monet.calendar.extensions.mo
monet/calendar/extensions/locales/it/LC_MESSAGES/monet.calendar.extensions.po
monet/calendar/extensions/profiles/default/browserlayer.xml
monet/calendar/extensions/profiles/default/catalog.xml
monet/calendar/extensions/profiles/default/cssregistry.xml
monet/calendar/extensions/profiles/default/jsregistry.xml
monet/calendar/extensions/profiles/default/metadata.xml
monet/calendar/extensions/profiles/default/monet.calendar.extensions-various.txt
monet/calendar/extensions/profiles/default/propertiestool.xml
monet/calendar/extensions/profiles/default/types.xml
monet/calendar/extensions/profiles/default/viewlets.xml
