Metadata-Version: 1.0
Name: monet.calendar.extensions
Version: 0.10.0
Summary: Provide additional search features for monet.calendar.star solution
Home-page: http://plone.org/products/monet.calendar.star
Author: RedTurtle Technology
Author-email: sviluppoplone@redturtle.it
License: GPL
Keywords: plone plonegov calendar event
Platform: UNKNOWN
Classifier: Framework :: Plone
Classifier: Framework :: Plone :: 4.2
Classifier: Framework :: Plone :: 4.3
Classifier: Programming Language :: Python
Classifier: License :: OSI Approved :: GNU General Public License (GPL)
